{"cameraMode":{"drawMode":0,"name":"Shaded","section":"Shading Mode"},"sceneLighting":true,"audioPlay":false,"sceneViewState":{"m_AlwaysRefresh":false,"showFog":true,"showSkybox":true,"showFlares":true,"showImageEffects":true,"showParticleSystems":true,"showVisualEffectGraphs":true,"m_FxEnabled":true},"in2DMode":false,"pivot":{"x":-0.7118059396743774,"y":4.9067912101745609,"z":-9.877853393554688},"rotation":{"x":-0.005700546316802502,"y":0.014827750623226166,"z":0.000033149368391605094,"w":0.9998234510421753},"size":8.913972854614258,"orthographic":false}